{
  "sverrirarnors/typst-math": {
    "createdAt": "2024-11-19T12:53:42Z",
    "defaultBranchRef": "main",
    "description": "No description available.",
    "latestRelease": "none",
    "latestReleaseUrl": null,
    "licenseInfo": "none",
    "name": "typst-math",
    "nameWithOwner": "sverrirarnors/typst-math",
    "openGraphImageUrl": "https://opengraph.githubassets.com/15d65eea77784928d99373bce6b0b7b71853d43084348de712ce9b297a273b0d/sverrirarnors/typst-math",
    "owner": "sverrirarnors",
    "pushedAt": "2024-11-19T14:15:41Z",
    "repositoryTopics": [
      "example"
    ],
    "stargazerCount": 10,
    "title": "TYPST MATH",
    "updatedAt": "2026-02-15T19:45:29Z",
    "url": "https://github.com/sverrirarnors/typst-math",
    "author": "Sverrir Arnórsson",
    "template": false,
    "example": true,
    "latestCommit": "bd288d6944f39600d8e5d5c5cd923fd31a9a0196",
    "contributes": [
      "filter"
    ],
    "quartoRequired": ">=1.5.0"
  }
}
