{
  "kazuyanagimoto/quarto-clean-typst": {
    "createdAt": "2024-07-29T22:23:51Z",
    "defaultBranchRef": "main",
    "description": "A minimalistic presentation theme for Quarto + Typst by Touying",
    "latestRelease": "v0.4.5",
    "latestReleaseUrl": "https://github.com/kazuyanagimoto/quarto-clean-typst/releases/tag/v0.4.5",
    "licenseInfo": "MIT License",
    "name": "quarto-clean-typst",
    "nameWithOwner": "kazuyanagimoto/quarto-clean-typst",
    "openGraphImageUrl": "https://opengraph.githubassets.com/81950c4c1ba06249199522cada4166d2b106a28deac53591aed0407a88849dc7/kazuyanagimoto/quarto-clean-typst",
    "owner": "kazuyanagimoto",
    "pushedAt": "2026-01-25T02:44:32Z",
    "repositoryTopics": [
      "touying",
      "typst",
      "template"
    ],
    "stargazerCount": 130,
    "title": "CLEAN TYPST",
    "updatedAt": "2026-02-26T18:56:02Z",
    "url": "https://github.com/kazuyanagimoto/quarto-clean-typst",
    "author": "Kazuharu Yanagimoto",
    "template": true,
    "example": false,
    "latestCommit": "8b2cf0215232c94cd2486bbd98e4cdbcf96d18af",
    "contributes": [
      "format"
    ],
    "quartoRequired": ">=1.8.0"
  }
}
