{
  "emilhvitfeldt/quarto-revealjs-letterbox": {
    "createdAt": "2022-12-06T22:27:16Z",
    "defaultBranchRef": "main",
    "description": "A Quarto reveal.js theme based on xaringan letterbox",
    "latestRelease": "3.0.0",
    "latestReleaseUrl": "https://github.com/EmilHvitfeldt/quarto-revealjs-letterbox/releases/tag/3.0.0",
    "licenseInfo": "MIT License",
    "name": "quarto-revealjs-letterbox",
    "nameWithOwner": "emilhvitfeldt/quarto-revealjs-letterbox",
    "openGraphImageUrl": "https://opengraph.githubassets.com/8214104c0db9a3f152550b2eceeb0dc3f474f7247b2518c8a51be29d5e82db7d/EmilHvitfeldt/quarto-revealjs-letterbox",
    "owner": "emilhvitfeldt",
    "pushedAt": "2025-06-04T14:57:39Z",
    "repositoryTopics": [
      "reveal.js",
      "template"
    ],
    "stargazerCount": 42,
    "title": "REVEALJS LETTERBOX",
    "updatedAt": "2026-01-30T05:05:41Z",
    "url": "https://github.com/EmilHvitfeldt/quarto-revealjs-letterbox",
    "author": "Emil Hvitfeldt",
    "template": true,
    "example": false,
    "latestCommit": "90b75cfe41c33a31836433c0ff34ed16b9b0ddf0",
    "contributes": [
      "format"
    ],
    "quartoRequired": null
  }
}
