{
  "pandoc-ext/list-table": {
    "createdAt": "2023-04-07T16:42:51Z",
    "defaultBranchRef": "main",
    "description": "Write tables as list of cells and rows.",
    "latestRelease": "v1.0.0",
    "latestReleaseUrl": "https://github.com/pandoc-ext/list-table/releases/tag/v1.0.0",
    "licenseInfo": "MIT License",
    "name": "list-table",
    "nameWithOwner": "pandoc-ext/list-table",
    "openGraphImageUrl": "https://opengraph.githubassets.com/dc1c10b17ef08ff0f871fe55cf4ce8a516202a7f3eb46e691c41fc04752932a8/pandoc-ext/list-table",
    "owner": "pandoc-ext",
    "pushedAt": "2024-11-28T15:59:00Z",
    "repositoryTopics": [
      "lua",
      "pandoc",
      "pandoc-filter"
    ],
    "stargazerCount": 41,
    "title": "LIST TABLE",
    "updatedAt": "2026-01-31T18:55:11Z",
    "url": "https://github.com/pandoc-ext/list-table",
    "author": "Pandoc Extensions",
    "template": false,
    "example": false,
    "latestCommit": "5f6d1a809c5f34a4d1986e9c216fab29e6c8c79a",
    "contributes": [
      "filter"
    ],
    "quartoRequired": ">=1.3"
  }
}
