{
  "edvinsyk/quarto-landscape": {
    "createdAt": "2024-08-20T15:01:25Z",
    "defaultBranchRef": "main",
    "description": "Filter for quarto that unifies the control of page orientation in a unified way between docx, pdf, and typst",
    "latestRelease": "none",
    "latestReleaseUrl": null,
    "licenseInfo": "none",
    "name": "quarto-landscape",
    "nameWithOwner": "edvinsyk/quarto-landscape",
    "openGraphImageUrl": "https://opengraph.githubassets.com/b5ba1a806950438f2a17e53a6c3215da159145cc501c3008889463b0b0abfc01/edvinsyk/quarto-landscape",
    "owner": "edvinsyk",
    "pushedAt": "2024-08-24T08:34:28Z",
    "repositoryTopics": [
      "article",
      "pandoc-filter",
      "writing",
      "example"
    ],
    "stargazerCount": 4,
    "title": "LANDSCAPE",
    "updatedAt": "2025-10-18T15:21:12Z",
    "url": "https://github.com/edvinsyk/quarto-landscape",
    "author": "Edvin Syk",
    "template": false,
    "example": true,
    "latestCommit": "c0091a63be5f4b7d66b4d35411357c4ff94fff4d",
    "contributes": [
      "filter"
    ],
    "quartoRequired": ">=1.6.0"
  }
}
