{
  "nessan/simple-vars": {
    "createdAt": "2024-08-19T17:16:26Z",
    "defaultBranchRef": "main",
    "description": "Quarto extension to allow simpler variable references in markup.",
    "latestRelease": "none",
    "latestReleaseUrl": null,
    "licenseInfo": "MIT License",
    "name": "simple-vars",
    "nameWithOwner": "nessan/simple-vars",
    "openGraphImageUrl": "https://opengraph.githubassets.com/0a1f849db1a03734d87a72b255afb1306b90f23533cecab7c7067ab19b599294/nessan/simple-vars",
    "owner": "nessan",
    "pushedAt": "2024-12-01T17:33:49Z",
    "repositoryTopics": [],
    "stargazerCount": 1,
    "title": "SIMPLE VARS",
    "updatedAt": "2024-12-01T17:33:52Z",
    "url": "https://github.com/nessan/simple-vars",
    "author": "Nessan",
    "template": false,
    "example": false,
    "latestCommit": "a738987d36267df1ba8d2d0c83e4bca4fc2b346b",
    "contributes": [
      "filter"
    ],
    "quartoRequired": ">=1.5.0"
  }
}
