{
  "danmackinlay/quarto_tikz": {
    "createdAt": "2024-02-19T06:58:54Z",
    "defaultBranchRef": "main",
    "description": "No description available.",
    "latestRelease": "none",
    "latestReleaseUrl": null,
    "licenseInfo": "MIT License",
    "name": "quarto_tikz",
    "nameWithOwner": "danmackinlay/quarto_tikz",
    "openGraphImageUrl": "https://opengraph.githubassets.com/cbbbe6232cadbbfc6760b044acfd0143ef43c2202f1884c1ec6132eadd68fb72/danmackinlay/quarto_tikz",
    "owner": "danmackinlay",
    "pushedAt": "2026-05-07T02:49:24Z",
    "repositoryTopics": [
      "example"
    ],
    "stargazerCount": 28,
    "title": "TIKZ",
    "updatedAt": "2026-05-07T02:49:28Z",
    "url": "https://github.com/danmackinlay/quarto_tikz",
    "author": "dan mackinlay",
    "template": false,
    "example": true,
    "latestCommit": "ea76b5332c51fae631d9322c4a974b61c9ca8a3e",
    "contributes": [
      "filter"
    ],
    "quartoRequired": ">=1.3.0"
  }
}
