{
  "rpodcast/quarto-revealjs-terminal": {
    "createdAt": "2026-06-07T03:32:30Z",
    "defaultBranchRef": "main",
    "description": "Quarto revealjs theme with retro terminal style",
    "latestRelease": "v0.1.0",
    "latestReleaseUrl": "https://github.com/rpodcast/quarto-revealjs-terminal/releases/tag/v0.1.0",
    "licenseInfo": "MIT License",
    "name": "quarto-revealjs-terminal",
    "nameWithOwner": "rpodcast/quarto-revealjs-terminal",
    "openGraphImageUrl": "https://opengraph.githubassets.com/4535e6f4002b9c126a3490da93a965f2d6733d3c1124bf8fa8d2376cee1772c4/rpodcast/quarto-revealjs-terminal",
    "owner": "rpodcast",
    "pushedAt": "2026-06-19T12:53:59Z",
    "repositoryTopics": [
      "reveal.js",
      "theme",
      "template"
    ],
    "stargazerCount": 3,
    "title": "REVEALJS TERMINAL",
    "updatedAt": "2026-06-19T20:53:51Z",
    "url": "https://github.com/rpodcast/quarto-revealjs-terminal",
    "author": "Eric Nantz",
    "template": true,
    "example": false,
    "latestCommit": "9acb02ef9bb3ae47fa0c89083fbbe73b054fdb55",
    "contributes": [
      "format"
    ],
    "quartoRequired": ">=1.4.0"
  }
}
