{
  "coatless-quarto/stanford": {
    "createdAt": "2024-04-22T05:01:44Z",
    "defaultBranchRef": "main",
    "description": "Unofficial Stanford University-themed Beamer, HTML, and RevealJS Extension for Quarto",
    "latestRelease": "none",
    "latestReleaseUrl": null,
    "licenseInfo": "Other",
    "name": "stanford",
    "nameWithOwner": "coatless-quarto/stanford",
    "openGraphImageUrl": "https://opengraph.githubassets.com/2bded683ffb49833659bcfecea8b0794e1f978a336329bee68fadc32a89fc1a5/coatless-quarto/stanford",
    "owner": "coatless-quarto",
    "pushedAt": "2024-05-30T05:07:27Z",
    "repositoryTopics": [
      "beamer",
      "html",
      "reveal.js",
      "stanford",
      "stanford-university"
    ],
    "stargazerCount": 10,
    "title": "STANFORD",
    "updatedAt": "2026-04-16T18:08:33Z",
    "url": "https://github.com/coatless-quarto/stanford",
    "author": "Various Extensions for Quarto",
    "template": false,
    "example": false,
    "latestCommit": "a35eb826abe9fb97c20dfd27d3699154546b87cd",
    "contributes": [
      "format"
    ],
    "quartoRequired": ">=1.4.0"
  }
}
