{
  "coatless-quarto/custom-callout": {
    "createdAt": "2024-10-18T06:43:54Z",
    "defaultBranchRef": "main",
    "description": "Quarto Extension to Setup Custom Callouts",
    "latestRelease": "0.0.1",
    "latestReleaseUrl": "https://github.com/coatless-quarto/custom-callout/releases/tag/0.0.1",
    "licenseInfo": "none",
    "name": "custom-callout",
    "nameWithOwner": "coatless-quarto/custom-callout",
    "openGraphImageUrl": "https://opengraph.githubassets.com/6909ce2d0f485ae0f238a81e7c3742383b09e68045221acac80fd79ae68126ab/coatless-quarto/custom-callout",
    "owner": "coatless-quarto",
    "pushedAt": "2025-05-30T21:28:21Z",
    "repositoryTopics": [
      "callout"
    ],
    "stargazerCount": 50,
    "title": "CUSTOM CALLOUT",
    "updatedAt": "2026-02-04T16:17:54Z",
    "url": "https://github.com/coatless-quarto/custom-callout",
    "author": "Various Extensions for Quarto",
    "template": false,
    "templateContent": null,
    "example": false,
    "exampleContent": null,
    "latestCommit": "95e8c9fa387c8a0b1b6b4984042c43fb67c06b11",
    "contributes": [
      "filter"
    ],
    "quartoRequired": ">=1.5.0"
  }
}
