{"login":"edvinsyk","id":65397052,"node_id":"MDQ6VXNlcjY1Mzk3MDUy","avatar_url":"https://avatars.githubusercontent.com/u/65397052?v=4","gravatar_id":"","url":"https://api.github.com/users/edvinsyk","html_url":"https://github.com/edvinsyk","followers_url":"https://api.github.com/users/edvinsyk/followers","following_url":"https://api.github.com/users/edvinsyk/following{/other_user}","gists_url":"https://api.github.com/users/edvinsyk/gists{/gist_id}","starred_url":"https://api.github.com/users/edvinsyk/starred{/owner}{/repo}","subscriptions_url":"https://api.github.com/users/edvinsyk/subscriptions","organizations_url":"https://api.github.com/users/edvinsyk/orgs","repos_url":"https://api.github.com/users/edvinsyk/repos","events_url":"https://api.github.com/users/edvinsyk/events{/privacy}","received_events_url":"https://api.github.com/users/edvinsyk/received_events","type":"User","user_view_type":"public","site_admin":false,"name":"Edvin Syk","company":null,"blog":"https://edvinsyk.github.io/","location":null,"email":null,"hireable":null,"bio":null,"twitter_username":null,"public_repos":5,"public_gists":0,"followers":2,"following":8,"created_at":"2020-05-15T10:04:04Z","updated_at":"2026-02-22T14:01:34Z"}
