{
  "coatless-quarto/colab": {
    "createdAt": "2024-06-12T21:40:38Z",
    "defaultBranchRef": "main",
    "description": "[Developmental] Quarto Extension to Enable Google Colaboratory Links with Quarto Documents ",
    "latestRelease": "none",
    "latestReleaseUrl": null,
    "licenseInfo": "none",
    "name": "colab",
    "nameWithOwner": "coatless-quarto/colab",
    "openGraphImageUrl": "https://opengraph.githubassets.com/d8e08c7a80eccec3aa86fe1d1708b1bda0ae32874a67e5172a3e4ceec5b68949/coatless-quarto/colab",
    "owner": "coatless-quarto",
    "pushedAt": "2025-05-18T21:15:34Z",
    "repositoryTopics": [
      "colab",
      "google-colab",
      "lua",
      "template"
    ],
    "stargazerCount": 16,
    "title": "COLAB",
    "updatedAt": "2026-04-05T08:56:02Z",
    "url": "https://github.com/coatless-quarto/colab",
    "author": "Various Extensions for Quarto",
    "template": true,
    "example": false,
    "latestCommit": "726beb45b649f908f52301a67dc69fa3765b20db",
    "contributes": [
      "filter"
    ],
    "quartoRequired": ">=1.4.0"
  }
}
