{
  "mcanouil/quarto-mcanouil": {
    "createdAt": "2025-08-14T08:39:12Z",
    "defaultBranchRef": "main",
    "description": "A Quarto extension that provides brand theming and styling for documents (HTML, Typst) and presentations (Reveal.js).",
    "latestRelease": "0.17.0",
    "latestReleaseUrl": "https://github.com/mcanouil/quarto-mcanouil/releases/tag/0.17.0",
    "licenseInfo": "MIT License",
    "name": "quarto-mcanouil",
    "nameWithOwner": "mcanouil/quarto-mcanouil",
    "openGraphImageUrl": "https://repository-images.githubusercontent.com/1037865694/e867c894-2e7d-418d-bffc-c969d5ace8d0",
    "owner": "mcanouil",
    "pushedAt": "2026-03-23T23:18:28Z",
    "repositoryTopics": [
      "brand",
      "brand-yml",
      "experimental",
      "example"
    ],
    "stargazerCount": 13,
    "title": "MCANOUIL",
    "updatedAt": "2026-03-23T23:16:17Z",
    "url": "https://github.com/mcanouil/quarto-mcanouil",
    "author": "Mickaël Canouil",
    "template": false,
    "example": true,
    "latestCommit": "88d7281f2b9b6f8fb838fadd78ff8b50b99912c9",
    "contributes": [
      "format",
      "metadata",
      "project"
    ],
    "quartoRequired": ">=1.9.20"
  }
}
