{
  "zachcp/quarto-swissbiopics": {
    "createdAt": "2022-12-12T13:55:01Z",
    "defaultBranchRef": "main",
    "description": "SwissBioPics in Quarto",
    "latestRelease": "none",
    "latestReleaseUrl": null,
    "licenseInfo": "none",
    "name": "quarto-swissbiopics",
    "nameWithOwner": "zachcp/quarto-swissbiopics",
    "openGraphImageUrl": "https://opengraph.githubassets.com/1f84a04b3e4fd7d3bc1c30cfaaf5f82251b0dbbed9515df000da254a10c79fcb/zachcp/quarto-swissbiopics",
    "owner": "zachcp",
    "pushedAt": "2022-12-28T17:41:02Z",
    "repositoryTopics": [],
    "stargazerCount": 2,
    "title": "SWISSBIOPICS",
    "updatedAt": "2023-01-28T08:44:27Z",
    "url": "https://github.com/zachcp/quarto-swissbiopics",
    "author": "null",
    "template": false,
    "templateContent": null,
    "example": false,
    "exampleContent": null,
    "latestCommit": "5613b6dd9a08ffc2950997f3f47e9d546e799751",
    "contributes": [
      "shortcode"
    ],
    "quartoRequired": ">=1.2.0"
  }
}
