{
  "schochastics/quarto-social-share": {
    "createdAt": "2022-08-10T06:57:54Z",
    "defaultBranchRef": "main",
    "description": "Quarto Extension that adds buttons to share on social media",
    "latestRelease": "none",
    "latestReleaseUrl": null,
    "licenseInfo": "MIT License",
    "name": "quarto-social-share",
    "nameWithOwner": "schochastics/quarto-social-share",
    "openGraphImageUrl": "https://opengraph.githubassets.com/1e4d5362586d5885a250e8ea962cf2545c97ac581ae779cd467a34657b021b8b/schochastics/quarto-social-share",
    "owner": "schochastics",
    "pushedAt": "2024-11-19T21:19:57Z",
    "repositoryTopics": [
      "example"
    ],
    "stargazerCount": 42,
    "title": "SOCIAL SHARE",
    "updatedAt": "2026-02-12T11:49:22Z",
    "url": "https://github.com/schochastics/quarto-social-share",
    "author": "David Schoch",
    "template": false,
    "example": true,
    "latestCommit": "c1a817cfe56348340a0dd3a25a24a445332f7d64",
    "contributes": [
      "filter",
      "shortcode"
    ],
    "quartoRequired": ">=1.2.269"
  }
}
