{
  "martinomagnifico/quarto-appearance": {
    "createdAt": "2023-05-10T10:38:50Z",
    "defaultBranchRef": "main",
    "description": "An animation plugin for Reveal.js that animates elements sequentially like in Powerpoint. Perfect for online portfolios or other presentations with images.",
    "latestRelease": "v1.4.0",
    "latestReleaseUrl": "https://github.com/Martinomagnifico/quarto-appearance/releases/tag/v1.4.0",
    "licenseInfo": "none",
    "name": "quarto-appearance",
    "nameWithOwner": "martinomagnifico/quarto-appearance",
    "openGraphImageUrl": "https://opengraph.githubassets.com/068e4c23945c712017d1645dc5ca267c4b3bca1c5f2c45e1e49e312277e47afb/Martinomagnifico/quarto-appearance",
    "owner": "martinomagnifico",
    "pushedAt": "2026-02-07T09:21:38Z",
    "repositoryTopics": [],
    "stargazerCount": 32,
    "title": "APPEARANCE",
    "updatedAt": "2026-02-09T14:39:27Z",
    "url": "https://github.com/Martinomagnifico/quarto-appearance",
    "author": "Martino",
    "template": false,
    "example": false,
    "latestCommit": "be62dad073c8edfc1df80588cd91bc5d3118855b",
    "contributes": [
      "revealjs-plugin"
    ],
    "quartoRequired": ">=1.2.198"
  }
}
