{
  "pandoc-ext/abstract-section": {
    "createdAt": "2022-08-25T12:42:53Z",
    "defaultBranchRef": "main",
    "description": "Write an article abstract in a normal section, not the YAML metadata.",
    "latestRelease": "v1.2.0",
    "latestReleaseUrl": "https://github.com/pandoc-ext/abstract-section/releases/tag/v1.2.0",
    "licenseInfo": "MIT License",
    "name": "abstract-section",
    "nameWithOwner": "pandoc-ext/abstract-section",
    "openGraphImageUrl": "https://opengraph.githubassets.com/083dcf7ac98e964f1d2ebc347a12871c1675cb02198be41098ce507bd0aec192/pandoc-ext/abstract-section",
    "owner": "pandoc-ext",
    "pushedAt": "2025-01-26T14:52:14Z",
    "repositoryTopics": [
      "filter",
      "pandoc-filter"
    ],
    "stargazerCount": 70,
    "title": "ABSTRACT SECTION",
    "updatedAt": "2026-06-11T21:24:35Z",
    "url": "https://github.com/pandoc-ext/abstract-section",
    "author": "Pandoc Extensions",
    "template": false,
    "example": false,
    "latestCommit": "481de0dec6ed2b5275dcb4dc30d169ff539d3d5a",
    "contributes": [
      "filter"
    ],
    "quartoRequired": null
  }
}
