{
  "qmd-lab/scheduled-docs": {
    "createdAt": "2024-04-05T23:07:16Z",
    "defaultBranchRef": "main",
    "description": "A Quarto Extension to schedule the publication of documents in websites and blogs.",
    "latestRelease": "none",
    "latestReleaseUrl": null,
    "licenseInfo": "MIT License",
    "name": "scheduled-docs",
    "nameWithOwner": "qmd-lab/scheduled-docs",
    "openGraphImageUrl": "https://opengraph.githubassets.com/02977836f48eb579f0fef5cb9aa3542f5a4534ecd5fcc484dac82131adf41a44/qmd-lab/scheduled-docs",
    "owner": "qmd-lab",
    "pushedAt": "2025-08-23T22:51:42Z",
    "repositoryTopics": [
      "blog",
      "pre-render",
      "project",
      "schedule",
      "website"
    ],
    "stargazerCount": 12,
    "title": "SCHEDULED DOCS",
    "updatedAt": "2025-10-22T19:53:50Z",
    "url": "https://github.com/qmd-lab/scheduled-docs",
    "author": "Qmd Lab",
    "template": false,
    "templateContent": null,
    "example": false,
    "exampleContent": null,
    "latestCommit": "6d6e1c2adb87435da95c004ff997d1077b3e2dd8",
    "contributes": [
      "metadata"
    ],
    "quartoRequired": ">=1.5.47"
  }
}
