{
  "nrichers/slideover": {
    "createdAt": "2025-03-30T17:20:36Z",
    "defaultBranchRef": "main",
    "description": "Add slide-over functionality to reveal.js presentations",
    "latestRelease": "none",
    "latestReleaseUrl": null,
    "licenseInfo": "MIT License",
    "name": "slideover",
    "nameWithOwner": "nrichers/slideover",
    "openGraphImageUrl": "https://opengraph.githubassets.com/3293568689d3cf7eb1b074f8cd83879238eb20bdf5cfd5af0be7990f50edf389/nrichers/slideover",
    "owner": "nrichers",
    "pushedAt": "2026-02-17T17:08:34Z",
    "repositoryTopics": [],
    "stargazerCount": 0,
    "title": "SLIDEOVER",
    "updatedAt": "2026-02-17T17:08:38Z",
    "url": "https://github.com/nrichers/slideover",
    "author": "Nik Richers",
    "template": false,
    "example": false,
    "latestCommit": "7a7e013a592bbf5ef8f2d4560e8184f7e02a1e49",
    "contributes": [
      "revealjs-plugin"
    ],
    "quartoRequired": ">=1.6.0"
  }
}
